{
    "mode": "hhcw",
    "chart": {
        "null": null,
        "100025": 12,
        "100026": 152,
        "100027": 54
    },
    "images": [
        "https://sirekap-obj-formc.kpu.go.id/99ac/pemilu/ppwp/33/18/19/20/16/3318192016002-20240217-101004--83d4f8f3-50d5-486f-bd9f-c9f8d732b492.jpg",
        "https://sirekap-obj-formc.kpu.go.id/99ac/pemilu/ppwp/33/18/19/20/16/3318192016002-20240217-101005--05a6faaf-bf86-4419-9314-ccd64c24039c.jpg",
        "https://sirekap-obj-formc.kpu.go.id/99ac/pemilu/ppwp/33/18/19/20/16/3318192016002-20240214-155824--50e7d151-3a64-4571-ae77-6d06b52ce4d4.jpg"
    ],
    "administrasi": {
        "suara_sah": 218,
        "suara_total": 224,
        "pemilih_dpt_j": 262,
        "pemilih_dpt_l": 130,
        "pemilih_dpt_p": 132,
        "pengguna_dpt_j": 223,
        "pengguna_dpt_l": 105,
        "pengguna_dpt_p": 118,
        "pengguna_dptb_j": 1,
        "pengguna_dptb_l": 0,
        "pengguna_dptb_p": 1,
        "suara_tidak_sah": 6,
        "pengguna_total_j": 224,
        "pengguna_total_l": 105,
        "pengguna_total_p": 119,
        "pengguna_non_dpt_j": 0,
        "pengguna_non_dpt_l": 0,
        "pengguna_non_dpt_p": 0
    },
    "psu": null,
    "ts": "2024-02-17 11:00:02",
    "status_suara": true,
    "status_adm": true
}