{
    "chart": {
        "null": null,
        "100025": 153,
        "100026": 18,
        "100027": 0
    },
    "images": [
        "https://sirekap-obj-formc.kpu.go.id/c24f/pemilu/ppwp/11/06/16/20/10/1106162010001-20240216-002016--64b33cee-3a64-4553-8a41-b140ab2655eb.jpg",
        "https://sirekap-obj-formc.kpu.go.id/c24f/pemilu/ppwp/11/06/16/20/10/1106162010001-20240216-002017--631d6fbb-026d-4de9-bd42-3c1069de1ac5.jpg",
        "https://sirekap-obj-formc.kpu.go.id/c24f/pemilu/ppwp/11/06/16/20/10/1106162010001-20240216-002016--70efaef7-1e6a-41a1-b146-31bacac41902.jpg"
    ],
    "administrasi": {
        "suara_sah": 171,
        "suara_total": 175,
        "pemilih_dpt_j": 187,
        "pemilih_dpt_l": 94,
        "pemilih_dpt_p": 93,
        "pengguna_dpt_j": 174,
        "pengguna_dpt_l": 89,
        "pengguna_dpt_p": 85,
        "pengguna_dptb_j": 0,
        "pengguna_dptb_l": 0,
        "pengguna_dptb_p": 0,
        "suara_tidak_sah": 4,
        "pengguna_total_j": 175,
        "pengguna_total_l": 89,
        "pengguna_total_p": 86,
        "pengguna_non_dpt_j": 1,
        "pengguna_non_dpt_l": 0,
        "pengguna_non_dpt_p": 1
    },
    "psu": null,
    "ts": "2024-02-16 01:00:27",
    "status_suara": true,
    "status_adm": true
}