{
    "mode": "hhcw",
    "chart": {
        "null": null,
        "100025": 9,
        "100026": 107,
        "100027": 46
    },
    "images": [
        "https://sirekap-obj-formc.kpu.go.id/90af/pemilu/ppwp/61/03/10/20/10/6103102010008-20240215-040744--4f2ecec5-b438-4b93-b0a6-9a0a5d9d3a28.jpg",
        "https://sirekap-obj-formc.kpu.go.id/90af/pemilu/ppwp/61/03/10/20/10/6103102010008-20240215-040930--54accf84-2352-487e-868d-4561d10bfa9f.jpg",
        "https://sirekap-obj-formc.kpu.go.id/90af/pemilu/ppwp/61/03/10/20/10/6103102010008-20240215-041022--268c0e1f-cff6-48af-a315-e07a6fd7b037.jpg"
    ],
    "administrasi": {
        "suara_sah": 162,
        "suara_total": 162,
        "pemilih_dpt_j": 168,
        "pemilih_dpt_l": 887,
        "pemilih_dpt_p": 890,
        "pengguna_dpt_j": 152,
        "pengguna_dpt_l": 78,
        "pengguna_dpt_p": 74,
        "pengguna_dptb_j": 8,
        "pengguna_dptb_l": 5,
        "pengguna_dptb_p": 3,
        "suara_tidak_sah": 0,
        "pengguna_total_j": 162,
        "pengguna_total_l": 84,
        "pengguna_total_p": 78,
        "pengguna_non_dpt_j": 2,
        "pengguna_non_dpt_l": 1,
        "pengguna_non_dpt_p": 1
    },
    "psu": null,
    "ts": "2024-02-16 23:00:00",
    "status_suara": true,
    "status_adm": true
}