{
    "mode": "hhcw",
    "chart": {
        "null": null,
        "100025": 41,
        "100026": 107,
        "100027": 10
    },
    "images": [
        "https://sirekap-obj-formc.kpu.go.id/e028/pemilu/ppwp/73/12/02/20/05/7312022005001-20240215-092002--ba0cc163-cabc-48a8-9d8a-7526463e4e1f.jpg",
        "https://sirekap-obj-formc.kpu.go.id/e028/pemilu/ppwp/73/12/02/20/05/7312022005001-20240217-121604--f1300ef6-6a7b-41ed-befc-cb9d570d5542.jpg",
        "https://sirekap-obj-formc.kpu.go.id/e028/pemilu/ppwp/73/12/02/20/05/7312022005001-20240214-212112--f568d66a-f1d6-40f7-9c0e-f9871568b5d7.jpg"
    ],
    "administrasi": {
        "suara_sah": 158,
        "suara_total": 160,
        "pemilih_dpt_j": 201,
        "pemilih_dpt_l": 87,
        "pemilih_dpt_p": 114,
        "pengguna_dpt_j": 152,
        "pengguna_dpt_l": 66,
        "pengguna_dpt_p": 86,
        "pengguna_dptb_j": 7,
        "pengguna_dptb_l": 6,
        "pengguna_dptb_p": 1,
        "suara_tidak_sah": 2,
        "pengguna_total_j": 160,
        "pengguna_total_l": 72,
        "pengguna_total_p": 88,
        "pengguna_non_dpt_j": 1,
        "pengguna_non_dpt_l": 0,
        "pengguna_non_dpt_p": 1
    },
    "psu": null,
    "ts": "2024-02-17 13:37:34",
    "status_suara": true,
    "status_adm": true
}