{
    "mode": "hhcw",
    "chart": {
        "null": null,
        "100025": 7,
        "100026": 107,
        "100027": 83
    },
    "images": [
        "https://sirekap-obj-formc.kpu.go.id/b7e6/pemilu/ppwp/35/01/01/20/08/3501012008006-20240216-214946--48f19fc7-a760-42c9-afdb-24851423bdb0.jpg",
        "https://sirekap-obj-formc.kpu.go.id/b7e6/pemilu/ppwp/35/01/01/20/08/3501012008006-20240216-214947--c977c81d-5b3f-4beb-a853-ae6a66cb2f2d.jpg",
        "https://sirekap-obj-formc.kpu.go.id/b7e6/pemilu/ppwp/35/01/01/20/08/3501012008006-20240216-214947--2c59d3d7-6af5-4d6b-8fc7-75c7030c104c.jpg"
    ],
    "administrasi": {
        "suara_sah": 197,
        "suara_total": 214,
        "pemilih_dpt_j": 280,
        "pemilih_dpt_l": 144,
        "pemilih_dpt_p": 136,
        "pengguna_dpt_j": 210,
        "pengguna_dpt_l": 106,
        "pengguna_dpt_p": 104,
        "pengguna_dptb_j": 0,
        "pengguna_dptb_l": 4,
        "pengguna_dptb_p": 0,
        "suara_tidak_sah": 17,
        "pengguna_total_j": 214,
        "pengguna_total_l": 110,
        "pengguna_total_p": 104,
        "pengguna_non_dpt_j": 0,
        "pengguna_non_dpt_l": 0,
        "pengguna_non_dpt_p": 0
    },
    "psu": null,
    "ts": "2024-02-16 22:30:00",
    "status_suara": true,
    "status_adm": true
}