{
    "chart": {
        "null": null,
        "100025": 106,
        "100026": 118,
        "100027": 22
    },
    "images": [
        "https://sirekap-obj-formc.kpu.go.id/e0fa/pemilu/ppwp/32/15/26/10/03/3215261003034-20240215-220005--563bb552-32bc-414c-bb43-78bdad07140e.jpg",
        "https://sirekap-obj-formc.kpu.go.id/e0fa/pemilu/ppwp/32/15/26/10/03/3215261003034-20240215-220007--ae76f61b-26d0-40df-98ff-8be0826bde7c.jpg",
        "https://sirekap-obj-formc.kpu.go.id/e0fa/pemilu/ppwp/32/15/26/10/03/3215261003034-20240215-220006--a81db135-8d1a-4202-8ce6-f511a4b9db5f.jpg"
    ],
    "administrasi": {
        "suara_sah": 246,
        "suara_total": 248,
        "pemilih_dpt_j": 248,
        "pemilih_dpt_l": 119,
        "pemilih_dpt_p": 129,
        "pengguna_dpt_j": 284,
        "pengguna_dpt_l": 136,
        "pengguna_dpt_p": 148,
        "pengguna_dptb_j": 0,
        "pengguna_dptb_l": 0,
        "pengguna_dptb_p": 0,
        "suara_tidak_sah": 2,
        "pengguna_total_j": 284,
        "pengguna_total_l": 136,
        "pengguna_total_p": 148,
        "pengguna_non_dpt_j": 0,
        "pengguna_non_dpt_l": 0,
        "pengguna_non_dpt_p": 0
    },
    "psu": null,
    "ts": "2024-02-16 10:30:29",
    "status_suara": true,
    "status_adm": true
}