{
    "mode": "hhcw",
    "chart": {
        "null": null,
        "100025": 37,
        "100026": 116,
        "100027": 10
    },
    "images": [
        "https://sirekap-obj-formc.kpu.go.id/e1b0/pemilu/ppwp/64/08/13/20/01/6408132001010-20240216-211342--436ffbd3-8bf5-45f8-862f-dc827845352d.jpg",
        "https://sirekap-obj-formc.kpu.go.id/e1b0/pemilu/ppwp/64/08/13/20/01/6408132001010-20240216-212019--becea848-8081-4d3b-9292-016a492cef5e.jpg",
        "https://sirekap-obj-formc.kpu.go.id/e1b0/pemilu/ppwp/64/08/13/20/01/6408132001010-20240216-212331--6fca88fc-d4c5-4b47-80ab-0f3d7b61386f.jpg"
    ],
    "administrasi": {
        "suara_sah": 163,
        "suara_total": 164,
        "pemilih_dpt_j": 225,
        "pemilih_dpt_l": 126,
        "pemilih_dpt_p": 99,
        "pengguna_dpt_j": 148,
        "pengguna_dpt_l": 77,
        "pengguna_dpt_p": 71,
        "pengguna_dptb_j": 1,
        "pengguna_dptb_l": 0,
        "pengguna_dptb_p": 1,
        "suara_tidak_sah": 1,
        "pengguna_total_j": 164,
        "pengguna_total_l": 83,
        "pengguna_total_p": 81,
        "pengguna_non_dpt_j": 15,
        "pengguna_non_dpt_l": 6,
        "pengguna_non_dpt_p": 9
    },
    "psu": null,
    "ts": "2024-02-17 11:30:03",
    "status_suara": true,
    "status_adm": true
}