{
    "mode": "hhcw",
    "chart": {
        "null": null,
        "100025": 49,
        "100026": 145,
        "100027": 32
    },
    "images": [
        "https://sirekap-obj-formc.kpu.go.id/5a99/pemilu/ppwp/35/10/16/10/02/3510161002015-20240218-114425--696bfb0e-ccaa-4904-a7f7-6d202a42a731.jpg",
        "https://sirekap-obj-formc.kpu.go.id/5a99/pemilu/ppwp/35/10/16/10/02/3510161002015-20240218-114426--6c2236eb-171e-43eb-ba56-831ab649e89c.jpg",
        "https://sirekap-obj-formc.kpu.go.id/5a99/pemilu/ppwp/35/10/16/10/02/3510161002015-20240218-114425--d54619fd-a5db-47d1-a19b-d1a600224d4d.jpg"
    ],
    "administrasi": {
        "suara_sah": 226,
        "suara_total": 227,
        "pemilih_dpt_j": 294,
        "pemilih_dpt_l": 138,
        "pemilih_dpt_p": 156,
        "pengguna_dpt_j": 218,
        "pengguna_dpt_l": 95,
        "pengguna_dpt_p": 123,
        "pengguna_dptb_j": 3,
        "pengguna_dptb_l": 1,
        "pengguna_dptb_p": 2,
        "suara_tidak_sah": 1,
        "pengguna_total_j": 227,
        "pengguna_total_l": 97,
        "pengguna_total_p": 130,
        "pengguna_non_dpt_j": 6,
        "pengguna_non_dpt_l": 1,
        "pengguna_non_dpt_p": 5
    },
    "psu": null,
    "ts": "2024-02-21 18:00:00",
    "status_suara": true,
    "status_adm": true
}