{
    "mode": "hhcw",
    "chart": {
        "null": null,
        "100025": 19,
        "100026": 165,
        "100027": 21
    },
    "images": [
        "https://sirekap-obj-formc.kpu.go.id/8f07/pemilu/ppwp/33/04/14/20/15/3304142015007-20240217-010412--01ed8ca0-0dd4-4e9b-9391-08b9fdc22080.jpg",
        "https://sirekap-obj-formc.kpu.go.id/8f07/pemilu/ppwp/33/04/14/20/15/3304142015007-20240217-010414--2b6978d8-a135-4159-aff9-f8567310731d.jpg",
        "https://sirekap-obj-formc.kpu.go.id/8f07/pemilu/ppwp/33/04/14/20/15/3304142015007-20240217-010413--f4cf4db9-1f14-4755-968f-9a3bb96d2232.jpg"
    ],
    "administrasi": {
        "suara_sah": 205,
        "suara_total": 212,
        "pemilih_dpt_j": 263,
        "pemilih_dpt_l": 134,
        "pemilih_dpt_p": 129,
        "pengguna_dpt_j": 204,
        "pengguna_dpt_l": 101,
        "pengguna_dpt_p": 103,
        "pengguna_dptb_j": 2,
        "pengguna_dptb_l": 1,
        "pengguna_dptb_p": 1,
        "suara_tidak_sah": 7,
        "pengguna_total_j": 212,
        "pengguna_total_l": 106,
        "pengguna_total_p": 106,
        "pengguna_non_dpt_j": 6,
        "pengguna_non_dpt_l": 4,
        "pengguna_non_dpt_p": 2
    },
    "psu": null,
    "ts": "2024-02-25 14:00:00",
    "status_suara": true,
    "status_adm": true
}