{
    "chart": {
        "null": null,
        "100025": 40,
        "100026": 120,
        "100027": 65
    },
    "images": [
        "https://sirekap-obj-formc.kpu.go.id/2c64/pemilu/ppwp/35/77/01/10/01/3577011001008-20240215-114621--0e6ec671-66e5-4190-95e9-a04354901054.jpg",
        "https://sirekap-obj-formc.kpu.go.id/2c64/pemilu/ppwp/35/77/01/10/01/3577011001008-20240215-114643--a8560094-9ff8-43dc-992b-a4481e23beaa.jpg",
        "https://sirekap-obj-formc.kpu.go.id/2c64/pemilu/ppwp/35/77/01/10/01/3577011001008-20240215-114632--d9031caf-4af9-4cef-bf1d-b757dbf08c0a.jpg"
    ],
    "administrasi": {
        "suara_sah": 225,
        "suara_total": 229,
        "pemilih_dpt_j": 274,
        "pemilih_dpt_l": 139,
        "pemilih_dpt_p": 135,
        "pengguna_dpt_j": 221,
        "pengguna_dpt_l": 103,
        "pengguna_dpt_p": 118,
        "pengguna_dptb_j": 8,
        "pengguna_dptb_l": 4,
        "pengguna_dptb_p": 4,
        "suara_tidak_sah": 4,
        "pengguna_total_j": 229,
        "pengguna_total_l": 107,
        "pengguna_total_p": 122,
        "pengguna_non_dpt_j": 0,
        "pengguna_non_dpt_l": 0,
        "pengguna_non_dpt_p": 0
    },
    "psu": null,
    "ts": "2024-02-15 19:30:26",
    "status_suara": true,
    "status_adm": true
}