{
    "mode": "hhcw",
    "chart": {
        "null": null,
        "100025": 120,
        "100026": 89,
        "100027": 13
    },
    "images": [
        "https://sirekap-obj-formc.kpu.go.id/7517/pemilu/ppwp/63/11/04/20/06/6311042006001-20240216-133852--f67235c1-8f57-4ca8-b6b1-26fe22f6427c.jpg",
        "https://sirekap-obj-formc.kpu.go.id/7517/pemilu/ppwp/63/11/04/20/06/6311042006001-20240216-133853--763bf7cb-ed31-4787-a64c-a5cd68b4694b.jpg",
        "https://sirekap-obj-formc.kpu.go.id/7517/pemilu/ppwp/63/11/04/20/06/6311042006001-20240216-133852--b93076ff-5467-4133-bf1a-38e3be7c2745.jpg"
    ],
    "administrasi": {
        "suara_sah": 222,
        "suara_total": 248,
        "pemilih_dpt_j": 283,
        "pemilih_dpt_l": 136,
        "pemilih_dpt_p": 147,
        "pengguna_dpt_j": 242,
        "pengguna_dpt_l": 119,
        "pengguna_dpt_p": 123,
        "pengguna_dptb_j": 5,
        "pengguna_dptb_l": 2,
        "pengguna_dptb_p": 3,
        "suara_tidak_sah": 26,
        "pengguna_total_j": 248,
        "pengguna_total_l": 121,
        "pengguna_total_p": 127,
        "pengguna_non_dpt_j": 1,
        "pengguna_non_dpt_l": 0,
        "pengguna_non_dpt_p": 1
    },
    "psu": null,
    "ts": "2024-02-16 22:30:00",
    "status_suara": true,
    "status_adm": true
}