{
    "chart": {
        "null": null,
        "100025": 37,
        "100026": 181,
        "100027": 96
    },
    "images": [
        "https://sirekap-obj-formc.kpu.go.id/3231/pemilu/ppwp/99/AG/01/00/01/99AG010001068-20240214-153829--261df7bd-6703-4e65-9c39-5468353fc601.jpg",
        "https://sirekap-obj-formc.kpu.go.id/3231/pemilu/ppwp/99/AG/01/00/01/99AG010001068-20240214-155150--7601b83a-353b-4225-8961-5cdf94f5b77c.jpg",
        "https://sirekap-obj-formc.kpu.go.id/3231/pemilu/ppwp/99/AG/01/00/01/99AG010001068-20240214-155121--4bdedeb0-2cbe-457b-a3c3-254a5c835e05.jpg"
    ],
    "administrasi": {
        "suara_sah": 314,
        "suara_total": 318,
        "pemilih_dpt_j": 962,
        "pemilih_dpt_l": 188,
        "pemilih_dpt_p": 774,
        "pengguna_dpt_j": 193,
        "pengguna_dpt_l": 44,
        "pengguna_dpt_p": 149,
        "pengguna_dptb_j": 10,
        "pengguna_dptb_l": 2,
        "pengguna_dptb_p": 8,
        "suara_tidak_sah": 4,
        "pengguna_total_j": 318,
        "pengguna_total_l": 76,
        "pengguna_total_p": 242,
        "pengguna_non_dpt_j": 115,
        "pengguna_non_dpt_l": 30,
        "pengguna_non_dpt_p": 85
    },
    "psu": null,
    "ts": "2024-02-14 21:46:01",
    "status_suara": true,
    "status_adm": true
}