{
    "chart": {
        "null": null,
        "100025": 56,
        "100026": 122,
        "100027": 35
    },
    "images": [
        "https://sirekap-obj-formc.kpu.go.id/5ffa/pemilu/ppwp/31/75/10/10/03/3175101003054-20240214-201626--b042b1c0-8980-44e8-85c8-7cd9f730bdc8.jpg",
        "https://sirekap-obj-formc.kpu.go.id/5ffa/pemilu/ppwp/31/75/10/10/03/3175101003054-20240214-201746--d1f8b05e-12aa-434a-8d33-010a2aa03f49.jpg",
        "https://sirekap-obj-formc.kpu.go.id/5ffa/pemilu/ppwp/31/75/10/10/03/3175101003054-20240214-201709--76bde7d8-63f0-4ab3-b046-9add193108d3.jpg"
    ],
    "administrasi": {
        "suara_sah": 213,
        "suara_total": 219,
        "pemilih_dpt_j": 263,
        "pemilih_dpt_l": 129,
        "pemilih_dpt_p": 134,
        "pengguna_dpt_j": 213,
        "pengguna_dpt_l": 101,
        "pengguna_dpt_p": 112,
        "pengguna_dptb_j": 5,
        "pengguna_dptb_l": 3,
        "pengguna_dptb_p": 2,
        "suara_tidak_sah": 6,
        "pengguna_total_j": 219,
        "pengguna_total_l": 104,
        "pengguna_total_p": 115,
        "pengguna_non_dpt_j": 1,
        "pengguna_non_dpt_l": 0,
        "pengguna_non_dpt_p": 1
    },
    "psu": null,
    "ts": "2024-02-15 04:00:24",
    "status_suara": true,
    "status_adm": true
}