{
    "chart": {
        "null": null,
        "100025": 22,
        "100026": 154,
        "100027": 35
    },
    "images": [
        "https://sirekap-obj-formc.kpu.go.id/da01/pemilu/ppwp/33/19/04/20/06/3319042006004-20240214-192905--68e20c48-6de9-4066-8097-3a06af80786e.jpg",
        "https://sirekap-obj-formc.kpu.go.id/da01/pemilu/ppwp/33/19/04/20/06/3319042006004-20240214-192911--c90aa391-6af8-4d4d-a379-e435eede725b.jpg",
        "https://sirekap-obj-formc.kpu.go.id/da01/pemilu/ppwp/33/19/04/20/06/3319042006004-20240214-192920--5b50c5d0-1208-4e11-8efd-290de423447a.jpg"
    ],
    "administrasi": {
        "suara_sah": 211,
        "suara_total": 216,
        "pemilih_dpt_j": 249,
        "pemilih_dpt_l": 120,
        "pemilih_dpt_p": 129,
        "pengguna_dpt_j": 214,
        "pengguna_dpt_l": 96,
        "pengguna_dpt_p": 118,
        "pengguna_dptb_j": 2,
        "pengguna_dptb_l": 1,
        "pengguna_dptb_p": 1,
        "suara_tidak_sah": 5,
        "pengguna_total_j": 216,
        "pengguna_total_l": 97,
        "pengguna_total_p": 119,
        "pengguna_non_dpt_j": 0,
        "pengguna_non_dpt_l": 0,
        "pengguna_non_dpt_p": 0
    },
    "psu": null,
    "ts": "2024-02-15 03:06:03",
    "status_suara": true,
    "status_adm": true
}