{
    "chart": {
        "null": null,
        "100025": 32,
        "100026": 178,
        "100027": 25
    },
    "images": [
        "https://sirekap-obj-formc.kpu.go.id/f411/pemilu/ppwp/35/15/06/20/19/3515062019009-20240214-193913--0c92ec27-70b9-4f43-874e-13446280aee7.jpg",
        "https://sirekap-obj-formc.kpu.go.id/f411/pemilu/ppwp/35/15/06/20/19/3515062019009-20240214-194004--f3caa094-8dc5-4045-89b9-b23c147b3cd7.jpg",
        "https://sirekap-obj-formc.kpu.go.id/f411/pemilu/ppwp/35/15/06/20/19/3515062019009-20240214-195912--bcd4622f-a6b2-43f4-8a50-83839ddd7237.jpg"
    ],
    "administrasi": {
        "suara_sah": 235,
        "suara_total": 243,
        "pemilih_dpt_j": 264,
        "pemilih_dpt_l": 143,
        "pemilih_dpt_p": 121,
        "pengguna_dpt_j": 241,
        "pengguna_dpt_l": 127,
        "pengguna_dpt_p": 114,
        "pengguna_dptb_j": 0,
        "pengguna_dptb_l": 0,
        "pengguna_dptb_p": 0,
        "suara_tidak_sah": 8,
        "pengguna_total_j": 243,
        "pengguna_total_l": 127,
        "pengguna_total_p": 116,
        "pengguna_non_dpt_j": 2,
        "pengguna_non_dpt_l": 0,
        "pengguna_non_dpt_p": 2
    },
    "psu": null,
    "ts": "2024-02-14 21:46:01",
    "status_suara": true,
    "status_adm": true
}