{
    "mode": "hhcw",
    "chart": {
        "null": null,
        "100025": 66,
        "100026": 122,
        "100027": 17
    },
    "images": [
        "https://sirekap-obj-formc.kpu.go.id/1907/pemilu/ppwp/52/06/07/20/06/5206072006003-20240216-215553--4b0b9ae8-ffd2-44ef-b0bb-50da94072bb6.jpg",
        "https://sirekap-obj-formc.kpu.go.id/1907/pemilu/ppwp/52/06/07/20/06/5206072006003-20240216-215554--e9ce778e-64a4-4d85-9d19-a43372a45635.jpg",
        "https://sirekap-obj-formc.kpu.go.id/1907/pemilu/ppwp/52/06/07/20/06/5206072006003-20240216-215553--82b7dca3-2580-49e2-a333-fb88e7535071.jpg"
    ],
    "administrasi": {
        "suara_sah": 205,
        "suara_total": 209,
        "pemilih_dpt_j": 235,
        "pemilih_dpt_l": 119,
        "pemilih_dpt_p": 116,
        "pengguna_dpt_j": 206,
        "pengguna_dpt_l": 100,
        "pengguna_dpt_p": 106,
        "pengguna_dptb_j": 2,
        "pengguna_dptb_l": 0,
        "pengguna_dptb_p": 2,
        "suara_tidak_sah": 4,
        "pengguna_total_j": 209,
        "pengguna_total_l": 101,
        "pengguna_total_p": 108,
        "pengguna_non_dpt_j": 1,
        "pengguna_non_dpt_l": 1,
        "pengguna_non_dpt_p": 0
    },
    "psu": null,
    "ts": "2024-02-19 06:16:00",
    "status_suara": true,
    "status_adm": true
}