{
    "chart": null,
    "images": [
        "https://sirekap-obj-formc.kpu.go.id/dbdc/pemilu/ppwp/32/01/15/20/03/3201152003023-20240215-033525--11698871-507b-4275-a00b-0fb355b5c651.jpg",
        null,
        "https://sirekap-obj-formc.kpu.go.id/dbdc/pemilu/ppwp/32/01/15/20/03/3201152003023-20240215-033535--e350cd7d-5f36-4fd7-8f40-11aeaf3ef667.jpg"
    ],
    "administrasi": {
        "suara_sah": 211,
        "suara_total": 218,
        "pemilih_dpt_j": 250,
        "pemilih_dpt_l": 129,
        "pemilih_dpt_p": 121,
        "pengguna_dpt_j": 215,
        "pengguna_dpt_l": 102,
        "pengguna_dpt_p": 113,
        "pengguna_dptb_j": 3,
        "pengguna_dptb_l": 1,
        "pengguna_dptb_p": 2,
        "suara_tidak_sah": 7,
        "pengguna_total_j": 218,
        "pengguna_total_l": 103,
        "pengguna_total_p": 115,
        "pengguna_non_dpt_j": 0,
        "pengguna_non_dpt_l": 0,
        "pengguna_non_dpt_p": 0
    },
    "psu": null,
    "ts": "2024-02-16 01:00:27",
    "status_suara": false,
    "status_adm": true
}