{
    "mode": "hhcw",
    "chart": {
        "null": null,
        "100025": 34,
        "100026": 143,
        "100027": 9
    },
    "images": [
        "https://sirekap-obj-formc.kpu.go.id/69e0/pemilu/ppwp/21/03/19/20/02/2103192002002-20240216-144828--fee301dc-2b43-4b7e-9282-d3cc42df3d66.jpg",
        "https://sirekap-obj-formc.kpu.go.id/69e0/pemilu/ppwp/21/03/19/20/02/2103192002002-20240216-144830--8e2342d1-0303-4ae2-b6e4-aa4436408d8a.jpg",
        "https://sirekap-obj-formc.kpu.go.id/69e0/pemilu/ppwp/21/03/19/20/02/2103192002002-20240216-144829--60a943d3-015f-4ee6-b2c2-784184f6e92e.jpg"
    ],
    "administrasi": {
        "suara_sah": 186,
        "suara_total": 191,
        "pemilih_dpt_j": 219,
        "pemilih_dpt_l": 113,
        "pemilih_dpt_p": 106,
        "pengguna_dpt_j": 188,
        "pengguna_dpt_l": 97,
        "pengguna_dpt_p": 91,
        "pengguna_dptb_j": 3,
        "pengguna_dptb_l": 0,
        "pengguna_dptb_p": 3,
        "suara_tidak_sah": 5,
        "pengguna_total_j": 191,
        "pengguna_total_l": 97,
        "pengguna_total_p": 94,
        "pengguna_non_dpt_j": 0,
        "pengguna_non_dpt_l": 0,
        "pengguna_non_dpt_p": 0
    },
    "psu": null,
    "ts": "2024-02-16 21:01:00",
    "status_suara": true,
    "status_adm": true
}