{
    "chart": {
        "null": null,
        "100025": 37,
        "100026": 126,
        "100027": 59
    },
    "images": [
        "https://sirekap-obj-formc.kpu.go.id/c695/pemilu/ppwp/15/03/05/20/17/1503052017002-20240215-083507--765f7c8a-6c99-4d9b-89c5-7241cb19eb79.jpg",
        "https://sirekap-obj-formc.kpu.go.id/c695/pemilu/ppwp/15/03/05/20/17/1503052017002-20240215-083744--92281cca-89fd-4d07-a605-c1bb755b1a9c.jpg",
        "https://sirekap-obj-formc.kpu.go.id/c695/pemilu/ppwp/15/03/05/20/17/1503052017002-20240215-083900--7e5820b1-8ae1-4040-b2c3-583de18cb6bc.jpg"
    ],
    "administrasi": {
        "suara_sah": 222,
        "suara_total": 225,
        "pemilih_dpt_j": 263,
        "pemilih_dpt_l": 138,
        "pemilih_dpt_p": 125,
        "pengguna_dpt_j": 217,
        "pengguna_dpt_l": 111,
        "pengguna_dpt_p": 106,
        "pengguna_dptb_j": 2,
        "pengguna_dptb_l": 1,
        "pengguna_dptb_p": 1,
        "suara_tidak_sah": 3,
        "pengguna_total_j": 225,
        "pengguna_total_l": 116,
        "pengguna_total_p": 109,
        "pengguna_non_dpt_j": 6,
        "pengguna_non_dpt_l": 4,
        "pengguna_non_dpt_p": 2
    },
    "psu": null,
    "ts": "2024-02-16 10:00:28",
    "status_suara": true,
    "status_adm": true
}