{
    "mode": "hhcw",
    "chart": {
        "null": null,
        "100025": 12,
        "100026": 123,
        "100027": 30
    },
    "images": [
        "https://sirekap-obj-formc.kpu.go.id/b4cc/pemilu/ppwp/64/07/13/20/03/6407132003001-20240216-140638--0529f578-8b47-4861-986d-9ae7da8b87a7.jpg",
        "https://sirekap-obj-formc.kpu.go.id/b4cc/pemilu/ppwp/64/07/13/20/03/6407132003001-20240216-140639--8289ec42-d052-4ff8-8433-f7bfa200f261.jpg",
        "https://sirekap-obj-formc.kpu.go.id/b4cc/pemilu/ppwp/64/07/13/20/03/6407132003001-20240216-140638--88613bea-b3e3-424b-b13c-674d50e697e4.jpg"
    ],
    "administrasi": {
        "suara_sah": 165,
        "suara_total": 172,
        "pemilih_dpt_j": 181,
        "pemilih_dpt_l": 98,
        "pemilih_dpt_p": 83,
        "pengguna_dpt_j": 169,
        "pengguna_dpt_l": 89,
        "pengguna_dpt_p": 80,
        "pengguna_dptb_j": 2,
        "pengguna_dptb_l": 1,
        "pengguna_dptb_p": 1,
        "suara_tidak_sah": 7,
        "pengguna_total_j": 172,
        "pengguna_total_l": 90,
        "pengguna_total_p": 82,
        "pengguna_non_dpt_j": 1,
        "pengguna_non_dpt_l": 0,
        "pengguna_non_dpt_p": 1
    },
    "psu": null,
    "ts": "2024-02-21 22:00:00",
    "status_suara": true,
    "status_adm": true
}