{
    "mode": "hhcw",
    "chart": {
        "null": null,
        "100025": 39,
        "100026": 128,
        "100027": 27
    },
    "images": [
        "https://sirekap-obj-formc.kpu.go.id/22b2/pemilu/ppwp/35/78/31/10/04/3578311004033-20240216-113111--b9059be7-356b-4e2b-a96b-5b4bb8de99f9.jpg",
        "https://sirekap-obj-formc.kpu.go.id/22b2/pemilu/ppwp/35/78/31/10/04/3578311004033-20240221-111734--b06ac3cb-c766-4bb2-9190-d24922ced8b3.jpg",
        "https://sirekap-obj-formc.kpu.go.id/22b2/pemilu/ppwp/35/78/31/10/04/3578311004033-20240221-111733--90682be3-440c-4ce7-8ced-479fdac484e3.jpg"
    ],
    "administrasi": {
        "suara_sah": 194,
        "suara_total": 196,
        "pemilih_dpt_j": 282,
        "pemilih_dpt_l": 150,
        "pemilih_dpt_p": 132,
        "pengguna_dpt_j": 195,
        "pengguna_dpt_l": 103,
        "pengguna_dpt_p": 92,
        "pengguna_dptb_j": 1,
        "pengguna_dptb_l": 0,
        "pengguna_dptb_p": 1,
        "suara_tidak_sah": 2,
        "pengguna_total_j": 196,
        "pengguna_total_l": 103,
        "pengguna_total_p": 93,
        "pengguna_non_dpt_j": 0,
        "pengguna_non_dpt_l": 0,
        "pengguna_non_dpt_p": 0
    },
    "psu": null,
    "ts": "2024-02-24 22:31:28",
    "status_suara": true,
    "status_adm": true
}