{
    "chart": {
        "null": null,
        "100025": 88,
        "100026": 108,
        "100027": 19
    },
    "images": [
        "https://sirekap-obj-formc.kpu.go.id/cf15/pemilu/ppwp/32/07/06/20/10/3207062010008-20240214-204229--57f51bfe-bd7b-4411-8e65-33fb5a2c306f.jpg",
        "https://sirekap-obj-formc.kpu.go.id/cf15/pemilu/ppwp/32/07/06/20/10/3207062010008-20240214-204322--3d2edff9-6b78-4be5-b442-43a9038af0b8.jpg",
        "https://sirekap-obj-formc.kpu.go.id/cf15/pemilu/ppwp/32/07/06/20/10/3207062010008-20240214-204454--e0f1c7e9-b2aa-4200-8fc8-b8960ea0a1bd.jpg"
    ],
    "administrasi": {
        "suara_sah": 215,
        "suara_total": 220,
        "pemilih_dpt_j": 245,
        "pemilih_dpt_l": 124,
        "pemilih_dpt_p": 121,
        "pengguna_dpt_j": 215,
        "pengguna_dpt_l": 108,
        "pengguna_dpt_p": 107,
        "pengguna_dptb_j": 0,
        "pengguna_dptb_l": 0,
        "pengguna_dptb_p": 0,
        "suara_tidak_sah": 5,
        "pengguna_total_j": 220,
        "pengguna_total_l": 110,
        "pengguna_total_p": 110,
        "pengguna_non_dpt_j": 5,
        "pengguna_non_dpt_l": 2,
        "pengguna_non_dpt_p": 3
    },
    "psu": null,
    "ts": "2024-02-15 12:00:28",
    "status_suara": true,
    "status_adm": true
}