{
    "mode": "hhcw",
    "chart": {
        "null": null,
        "100025": 104,
        "100026": 115,
        "100027": 12
    },
    "images": [
        "https://sirekap-obj-formc.kpu.go.id/ae31/pemilu/ppwp/32/14/01/20/10/3214012010025-20240216-130207--d9e6a5ef-1650-4a8c-9926-7fec18040f87.jpg",
        "https://sirekap-obj-formc.kpu.go.id/ae31/pemilu/ppwp/32/14/01/20/10/3214012010025-20240216-130213--2bf25b5e-2330-497b-972d-df5ed55fc1b9.jpg",
        "https://sirekap-obj-formc.kpu.go.id/ae31/pemilu/ppwp/32/14/01/20/10/3214012010025-20240216-130210--61648239-2b8d-4b3f-84b3-0bfb9da7c8fa.jpg"
    ],
    "administrasi": {
        "suara_sah": 231,
        "suara_total": 236,
        "pemilih_dpt_j": 266,
        "pemilih_dpt_l": 129,
        "pemilih_dpt_p": 137,
        "pengguna_dpt_j": 230,
        "pengguna_dpt_l": 111,
        "pengguna_dpt_p": 119,
        "pengguna_dptb_j": 5,
        "pengguna_dptb_l": 3,
        "pengguna_dptb_p": 2,
        "suara_tidak_sah": 5,
        "pengguna_total_j": 236,
        "pengguna_total_l": 114,
        "pengguna_total_p": 122,
        "pengguna_non_dpt_j": 1,
        "pengguna_non_dpt_l": 0,
        "pengguna_non_dpt_p": 1
    },
    "psu": null,
    "ts": "2024-02-19 16:00:00",
    "status_suara": true,
    "status_adm": true
}