{
    "mode": "hhcw",
    "chart": {
        "null": null,
        "100025": 78,
        "100026": 140,
        "100027": 53
    },
    "images": [
        "https://sirekap-obj-formc.kpu.go.id/f208/pemilu/ppwp/32/01/02/20/08/3201022008017-20240215-235612--3f94b1b5-64e1-44af-b583-51c3493c193f.jpg",
        "https://sirekap-obj-formc.kpu.go.id/f208/pemilu/ppwp/32/01/02/20/08/3201022008017-20240215-235613--ece0d2c0-3e97-4302-8a9f-3dd190875ccd.jpg",
        "https://sirekap-obj-formc.kpu.go.id/f208/pemilu/ppwp/32/01/02/20/08/3201022008017-20240215-235613--a57f6f1d-8ebd-4aa3-bc3d-d38097158dbd.jpg"
    ],
    "administrasi": {
        "suara_sah": 271,
        "suara_total": 279,
        "pemilih_dpt_j": 300,
        "pemilih_dpt_l": 151,
        "pemilih_dpt_p": 149,
        "pengguna_dpt_j": 250,
        "pengguna_dpt_l": 125,
        "pengguna_dpt_p": 125,
        "pengguna_dptb_j": 16,
        "pengguna_dptb_l": 7,
        "pengguna_dptb_p": 9,
        "suara_tidak_sah": 8,
        "pengguna_total_j": 279,
        "pengguna_total_l": 136,
        "pengguna_total_p": 143,
        "pengguna_non_dpt_j": 13,
        "pengguna_non_dpt_l": 4,
        "pengguna_non_dpt_p": 9
    },
    "psu": null,
    "ts": "2024-02-24 22:31:28",
    "status_suara": true,
    "status_adm": true
}