{
    "chart": {
        "null": null,
        "100025": 28,
        "100026": 201,
        "100027": 4
    },
    "images": [
        "https://sirekap-obj-formc.kpu.go.id/fab7/pemilu/ppwp/52/06/03/20/01/5206032001008-20240215-191452--c7538165-6f9a-4494-a840-7cb1a76e2602.jpg",
        "https://sirekap-obj-formc.kpu.go.id/fab7/pemilu/ppwp/52/06/03/20/01/5206032001008-20240215-191532--621fd0a2-7e86-4141-ac79-cf7ee5ae3676.jpg",
        "https://sirekap-obj-formc.kpu.go.id/fab7/pemilu/ppwp/52/06/03/20/01/5206032001008-20240215-191532--b618b152-4bde-4167-b411-a8e4145a8ab9.jpg"
    ],
    "administrasi": {
        "suara_sah": 233,
        "suara_total": 247,
        "pemilih_dpt_j": 290,
        "pemilih_dpt_l": 152,
        "pemilih_dpt_p": 138,
        "pengguna_dpt_j": 240,
        "pengguna_dpt_l": 119,
        "pengguna_dpt_p": 121,
        "pengguna_dptb_j": 4,
        "pengguna_dptb_l": 2,
        "pengguna_dptb_p": 2,
        "suara_tidak_sah": 14,
        "pengguna_total_j": 247,
        "pengguna_total_l": 121,
        "pengguna_total_p": 126,
        "pengguna_non_dpt_j": 3,
        "pengguna_non_dpt_l": 0,
        "pengguna_non_dpt_p": 3
    },
    "psu": null,
    "ts": "2024-02-16 14:00:34",
    "status_suara": true,
    "status_adm": true
}