{
    "chart": {
        "null": null,
        "100025": 81,
        "100026": 92,
        "100027": 8
    },
    "images": [
        "https://sirekap-obj-formc.kpu.go.id/3951/pemilu/ppwp/32/01/21/20/06/3201212006006-20240214-192235--5a5f2022-0d33-45bb-ad63-d5b46db2f2c6.jpg",
        "https://sirekap-obj-formc.kpu.go.id/3951/pemilu/ppwp/32/01/21/20/06/3201212006006-20240214-192513--0c8efbeb-cdbe-430e-a41b-5e7b220714f4.jpg",
        "https://sirekap-obj-formc.kpu.go.id/3951/pemilu/ppwp/32/01/21/20/06/3201212006006-20240214-192740--d37c8fab-861f-424f-9515-ed59a191866f.jpg"
    ],
    "administrasi": {
        "suara_sah": 181,
        "suara_total": 183,
        "pemilih_dpt_j": 228,
        "pemilih_dpt_l": 122,
        "pemilih_dpt_p": 106,
        "pengguna_dpt_j": 182,
        "pengguna_dpt_l": 90,
        "pengguna_dpt_p": 92,
        "pengguna_dptb_j": 1,
        "pengguna_dptb_l": 1,
        "pengguna_dptb_p": 0,
        "suara_tidak_sah": 2,
        "pengguna_total_j": 183,
        "pengguna_total_l": 91,
        "pengguna_total_p": 92,
        "pengguna_non_dpt_j": 0,
        "pengguna_non_dpt_l": 0,
        "pengguna_non_dpt_p": 0
    },
    "psu": null,
    "ts": "2024-02-14 21:46:01",
    "status_suara": true,
    "status_adm": true
}