{
    "mode": "hhcw",
    "chart": {
        "null": null,
        "100025": 21,
        "100026": 159,
        "100027": 51
    },
    "images": [
        "https://sirekap-obj-formc.kpu.go.id/6767/pemilu/ppwp/35/07/14/20/09/3507142009007-20240216-144435--de72a4d8-0b26-4e07-a03a-4a545dc9bc98.jpg",
        "https://sirekap-obj-formc.kpu.go.id/6767/pemilu/ppwp/35/07/14/20/09/3507142009007-20240216-144436--b591e8b9-50e1-4baa-82a0-6a8feab9347c.jpg",
        "https://sirekap-obj-formc.kpu.go.id/6767/pemilu/ppwp/35/07/14/20/09/3507142009007-20240216-144435--4262a05b-08ae-4621-9517-03fbaa2c6a60.jpg"
    ],
    "administrasi": {
        "suara_sah": 231,
        "suara_total": 236,
        "pemilih_dpt_j": 298,
        "pemilih_dpt_l": 141,
        "pemilih_dpt_p": 157,
        "pengguna_dpt_j": 233,
        "pengguna_dpt_l": 104,
        "pengguna_dpt_p": 129,
        "pengguna_dptb_j": 1,
        "pengguna_dptb_l": 1,
        "pengguna_dptb_p": 0,
        "suara_tidak_sah": 5,
        "pengguna_total_j": 236,
        "pengguna_total_l": 106,
        "pengguna_total_p": 130,
        "pengguna_non_dpt_j": 2,
        "pengguna_non_dpt_l": 1,
        "pengguna_non_dpt_p": 1
    },
    "psu": null,
    "ts": "2024-02-21 18:00:00",
    "status_suara": true,
    "status_adm": true
}