{
    "chart": {
        "null": null,
        "100025": 68,
        "100026": 133,
        "100027": 9
    },
    "images": [
        "https://sirekap-obj-formc.kpu.go.id/2a1e/pemilu/ppwp/32/16/11/20/01/3216112001008-20240214-201036--302537aa-3c9f-4b4c-a42d-77b1bc212851.jpg",
        "https://sirekap-obj-formc.kpu.go.id/2a1e/pemilu/ppwp/32/16/11/20/01/3216112001008-20240214-193913--5a7b6a6e-1fae-4cdd-9e32-ba8ecb0a4fc8.jpg",
        "https://sirekap-obj-formc.kpu.go.id/2a1e/pemilu/ppwp/32/16/11/20/01/3216112001008-20240214-193954--735c68c5-06d0-42cb-bd2b-1c76a91c6268.jpg"
    ],
    "administrasi": {
        "suara_sah": 210,
        "suara_total": 215,
        "pemilih_dpt_j": 251,
        "pemilih_dpt_l": 129,
        "pemilih_dpt_p": 122,
        "pengguna_dpt_j": 215,
        "pengguna_dpt_l": 107,
        "pengguna_dpt_p": 108,
        "pengguna_dptb_j": 0,
        "pengguna_dptb_l": 0,
        "pengguna_dptb_p": 0,
        "suara_tidak_sah": 5,
        "pengguna_total_j": 215,
        "pengguna_total_l": 107,
        "pengguna_total_p": 108,
        "pengguna_non_dpt_j": 0,
        "pengguna_non_dpt_l": 0,
        "pengguna_non_dpt_p": 0
    },
    "psu": null,
    "ts": "2024-02-15 00:41:44",
    "status_suara": true,
    "status_adm": true
}