{
    "mode": "hhcw",
    "chart": {
        "null": null,
        "100025": 13,
        "100026": 53,
        "100027": 68
    },
    "images": [
        "https://sirekap-obj-formc.kpu.go.id/3c62/pemilu/ppwp/33/28/02/20/12/3328022012005-20240219-205634--2c6547c9-2e5d-4b4e-8428-f766541cca18.jpg",
        "https://sirekap-obj-formc.kpu.go.id/3c62/pemilu/ppwp/33/28/02/20/12/3328022012005-20240219-222519--dcdb8ef9-909d-4233-ad6c-9e872b4f1fbc.jpg",
        "https://sirekap-obj-formc.kpu.go.id/3c62/pemilu/ppwp/33/28/02/20/12/3328022012005-20240219-220716--b2fc6d3c-ca23-4c9d-9da8-745fd4282129.jpg"
    ],
    "administrasi": {
        "suara_sah": 134,
        "suara_total": 138,
        "pemilih_dpt_j": 215,
        "pemilih_dpt_l": 116,
        "pemilih_dpt_p": 39,
        "pengguna_dpt_j": 138,
        "pengguna_dpt_l": 61,
        "pengguna_dpt_p": 17,
        "pengguna_dptb_j": 0,
        "pengguna_dptb_l": 0,
        "pengguna_dptb_p": 0,
        "suara_tidak_sah": 4,
        "pengguna_total_j": 138,
        "pengguna_total_l": 61,
        "pengguna_total_p": 17,
        "pengguna_non_dpt_j": 0,
        "pengguna_non_dpt_l": 0,
        "pengguna_non_dpt_p": 0
    },
    "psu": null,
    "ts": "2024-02-19 23:00:00",
    "status_suara": true,
    "status_adm": true
}