{
    "mode": "hhcw",
    "chart": {
        "null": null,
        "100025": 29,
        "100026": 168,
        "100027": 4
    },
    "images": [
        "https://sirekap-obj-formc.kpu.go.id/9cd8/pemilu/ppwp/74/11/02/10/01/7411021001001-20240216-210021--6d1afffa-9c94-4364-aee2-b51bc95abfc7.jpg",
        "https://sirekap-obj-formc.kpu.go.id/9cd8/pemilu/ppwp/74/11/02/10/01/7411021001001-20240216-210023--5cdee250-6b8f-4745-bcdb-ecc1dfc0a571.jpg",
        "https://sirekap-obj-formc.kpu.go.id/9cd8/pemilu/ppwp/74/11/02/10/01/7411021001001-20240216-210022--bf0b9e7d-9390-4f22-8c29-a07391b2cce9.jpg"
    ],
    "administrasi": {
        "suara_sah": 201,
        "suara_total": 207,
        "pemilih_dpt_j": 243,
        "pemilih_dpt_l": 129,
        "pemilih_dpt_p": 114,
        "pengguna_dpt_j": 201,
        "pengguna_dpt_l": 102,
        "pengguna_dpt_p": 99,
        "pengguna_dptb_j": 0,
        "pengguna_dptb_l": 0,
        "pengguna_dptb_p": 0,
        "suara_tidak_sah": 6,
        "pengguna_total_j": 207,
        "pengguna_total_l": 106,
        "pengguna_total_p": 101,
        "pengguna_non_dpt_j": 6,
        "pengguna_non_dpt_l": 4,
        "pengguna_non_dpt_p": 2
    },
    "psu": null,
    "ts": "2024-02-16 23:00:00",
    "status_suara": true,
    "status_adm": true
}