{
    "mode": "hhcw",
    "chart": {
        "null": null,
        "100025": 8,
        "100026": 99,
        "100027": 97
    },
    "images": [
        "https://sirekap-obj-formc.kpu.go.id/71b6/pemilu/ppwp/33/27/12/20/01/3327122001003-20240214-200707--5dfe38c5-3f1e-47c6-8698-86e4c10db248.jpg",
        "https://sirekap-obj-formc.kpu.go.id/71b6/pemilu/ppwp/33/27/12/20/01/3327122001003-20240214-201247--a24767b1-70a5-4200-b97d-9034d7e2681e.jpg",
        "https://sirekap-obj-formc.kpu.go.id/71b6/pemilu/ppwp/33/27/12/20/01/3327122001003-20240214-201449--10e56f74-adac-4a52-bcd2-905e2f5c1d1f.jpg"
    ],
    "administrasi": {
        "suara_sah": 204,
        "suara_total": 208,
        "pemilih_dpt_j": 279,
        "pemilih_dpt_l": 135,
        "pemilih_dpt_p": 144,
        "pengguna_dpt_j": 208,
        "pengguna_dpt_l": 93,
        "pengguna_dpt_p": 115,
        "pengguna_dptb_j": 0,
        "pengguna_dptb_l": 0,
        "pengguna_dptb_p": 0,
        "suara_tidak_sah": 4,
        "pengguna_total_j": 208,
        "pengguna_total_l": 93,
        "pengguna_total_p": 115,
        "pengguna_non_dpt_j": 0,
        "pengguna_non_dpt_l": 0,
        "pengguna_non_dpt_p": 0
    },
    "psu": null,
    "ts": "2024-02-17 18:00:00",
    "status_suara": true,
    "status_adm": true
}