{
    "chart": {
        "null": null,
        "100025": 63,
        "100026": 74,
        "100027": 36
    },
    "images": [
        "https://sirekap-obj-formc.kpu.go.id/0428/pemilu/ppwp/21/02/01/10/10/2102011010007-20240214-155900--94bab860-9155-40a1-8b96-17218419703e.jpg",
        "https://sirekap-obj-formc.kpu.go.id/0428/pemilu/ppwp/21/02/01/10/10/2102011010007-20240214-155723--165438ac-aad4-41dd-bd55-f7b174bc7f7d.jpg",
        "https://sirekap-obj-formc.kpu.go.id/0428/pemilu/ppwp/21/02/01/10/10/2102011010007-20240214-155831--c79f5c94-63e3-4075-8df6-28fa199b85a2.jpg"
    ],
    "administrasi": {
        "suara_sah": 173,
        "suara_total": 175,
        "pemilih_dpt_j": 267,
        "pemilih_dpt_l": 431,
        "pemilih_dpt_p": 136,
        "pengguna_dpt_j": 171,
        "pengguna_dpt_l": 78,
        "pengguna_dpt_p": 93,
        "pengguna_dptb_j": 4,
        "pengguna_dptb_l": 2,
        "pengguna_dptb_p": 2,
        "suara_tidak_sah": 2,
        "pengguna_total_j": 175,
        "pengguna_total_l": 80,
        "pengguna_total_p": 95,
        "pengguna_non_dpt_j": 0,
        "pengguna_non_dpt_l": 0,
        "pengguna_non_dpt_p": 0
    },
    "psu": null,
    "ts": "2024-02-14 21:46:01",
    "status_suara": true,
    "status_adm": true
}