{
    "mode": "hhcw",
    "chart": {
        "null": null,
        "100025": 64,
        "100026": 142,
        "100027": 14
    },
    "images": [
        "https://sirekap-obj-formc.kpu.go.id/1b73/pemilu/ppwp/16/73/08/10/05/1673081005003-20240216-142154--ba039d1e-b5ee-4d97-a529-f205f8a76479.jpg",
        "https://sirekap-obj-formc.kpu.go.id/1b73/pemilu/ppwp/16/73/08/10/05/1673081005003-20240216-142155--1b51a749-21a6-469a-944e-4582033d5962.jpg",
        "https://sirekap-obj-formc.kpu.go.id/1b73/pemilu/ppwp/16/73/08/10/05/1673081005003-20240216-142154--57ddb815-11dc-435e-82bc-8ef67a301563.jpg"
    ],
    "administrasi": {
        "suara_sah": 220,
        "suara_total": 229,
        "pemilih_dpt_j": 268,
        "pemilih_dpt_l": 129,
        "pemilih_dpt_p": 139,
        "pengguna_dpt_j": 229,
        "pengguna_dpt_l": 104,
        "pengguna_dpt_p": 125,
        "pengguna_dptb_j": 1,
        "pengguna_dptb_l": 1,
        "pengguna_dptb_p": 0,
        "suara_tidak_sah": 9,
        "pengguna_total_j": 234,
        "pengguna_total_l": 106,
        "pengguna_total_p": 128,
        "pengguna_non_dpt_j": 4,
        "pengguna_non_dpt_l": 1,
        "pengguna_non_dpt_p": 3
    },
    "psu": null,
    "ts": "2024-02-16 16:25:10",
    "status_suara": true,
    "status_adm": true
}