{
    "chart": {
        "null": null,
        "100025": 69,
        "100026": 121,
        "100027": 11
    },
    "images": [
        "https://sirekap-obj-formc.kpu.go.id/b449/pemilu/ppwp/12/09/19/10/03/1209191003006-20240214-155346--47b85948-4a8b-4f9f-bb9c-9f04bb3f76c6.jpg",
        "https://sirekap-obj-formc.kpu.go.id/b449/pemilu/ppwp/12/09/19/10/03/1209191003006-20240214-155533--286b883e-31ef-4bb9-ad10-c6eb4d33d3d5.jpg",
        "https://sirekap-obj-formc.kpu.go.id/b449/pemilu/ppwp/12/09/19/10/03/1209191003006-20240214-155408--3a51e172-1a72-4a6d-b015-c1fc3db546d1.jpg"
    ],
    "administrasi": {
        "suara_sah": 201,
        "suara_total": 202,
        "pemilih_dpt_j": 250,
        "pemilih_dpt_l": 118,
        "pemilih_dpt_p": 132,
        "pengguna_dpt_j": 198,
        "pengguna_dpt_l": 92,
        "pengguna_dpt_p": 106,
        "pengguna_dptb_j": 4,
        "pengguna_dptb_l": 2,
        "pengguna_dptb_p": 2,
        "suara_tidak_sah": 1,
        "pengguna_total_j": 202,
        "pengguna_total_l": 94,
        "pengguna_total_p": 108,
        "pengguna_non_dpt_j": 0,
        "pengguna_non_dpt_l": 0,
        "pengguna_non_dpt_p": 0
    },
    "psu": null,
    "ts": "2024-02-15 00:41:44",
    "status_suara": true,
    "status_adm": true
}