{
    "chart": {
        "null": null,
        "100025": 25,
        "100026": 107,
        "100027": 43
    },
    "images": [
        "https://sirekap-obj-formc.kpu.go.id/1c68/pemilu/ppwp/33/25/06/20/05/3325062005001-20240214-195056--695e2648-6e6d-47a6-9e1a-49418af4b43f.jpg",
        "https://sirekap-obj-formc.kpu.go.id/1c68/pemilu/ppwp/33/25/06/20/05/3325062005001-20240214-195414--248c6f1b-c74e-46e2-872b-673183ffca58.jpg",
        "https://sirekap-obj-formc.kpu.go.id/1c68/pemilu/ppwp/33/25/06/20/05/3325062005001-20240214-195419--3c85a937-da5c-44cd-8d21-ab12430aa47b.jpg"
    ],
    "administrasi": {
        "suara_sah": 175,
        "suara_total": 184,
        "pemilih_dpt_j": 215,
        "pemilih_dpt_l": 114,
        "pemilih_dpt_p": 101,
        "pengguna_dpt_j": 183,
        "pengguna_dpt_l": 100,
        "pengguna_dpt_p": 83,
        "pengguna_dptb_j": 0,
        "pengguna_dptb_l": 0,
        "pengguna_dptb_p": 0,
        "suara_tidak_sah": 9,
        "pengguna_total_j": 184,
        "pengguna_total_l": 100,
        "pengguna_total_p": 84,
        "pengguna_non_dpt_j": 1,
        "pengguna_non_dpt_l": 0,
        "pengguna_non_dpt_p": 1
    },
    "psu": null,
    "ts": "2024-02-15 00:41:44",
    "status_suara": true,
    "status_adm": true
}