{
    "mode": "hhcw",
    "chart": {
        "null": null,
        "100025": 17,
        "100026": 90,
        "100027": 91
    },
    "images": [
        "https://sirekap-obj-formc.kpu.go.id/d578/pemilu/ppwp/33/24/09/20/07/3324092007008-20240216-184345--8e444c44-021f-4163-a796-1cec79022fab.jpg",
        "https://sirekap-obj-formc.kpu.go.id/d578/pemilu/ppwp/33/24/09/20/07/3324092007008-20240216-184529--8d462eb0-14a9-48bb-a3e0-5c16eb734db7.jpg",
        "https://sirekap-obj-formc.kpu.go.id/d578/pemilu/ppwp/33/24/09/20/07/3324092007008-20240216-184724--a14bc0ed-f5ae-4e78-85a2-7241161cf988.jpg"
    ],
    "administrasi": {
        "suara_sah": 198,
        "suara_total": 201,
        "pemilih_dpt_j": 221,
        "pemilih_dpt_l": 111,
        "pemilih_dpt_p": 110,
        "pengguna_dpt_j": 192,
        "pengguna_dpt_l": 96,
        "pengguna_dpt_p": 96,
        "pengguna_dptb_j": 4,
        "pengguna_dptb_l": 2,
        "pengguna_dptb_p": 2,
        "suara_tidak_sah": 3,
        "pengguna_total_j": 201,
        "pengguna_total_l": 100,
        "pengguna_total_p": 101,
        "pengguna_non_dpt_j": 5,
        "pengguna_non_dpt_l": 2,
        "pengguna_non_dpt_p": 3
    },
    "psu": null,
    "ts": "2024-02-16 21:01:00",
    "status_suara": true,
    "status_adm": true
}