{
    "mode": "hhcw",
    "chart": {
        "null": null,
        "100025": 16,
        "100026": 137,
        "100027": 66
    },
    "images": [
        "https://sirekap-obj-formc.kpu.go.id/a603/pemilu/ppwp/35/10/02/20/07/3510022007015-20240215-005012--61960bfc-2f7b-43e4-a6a6-b5ea97376b7b.jpg",
        "https://sirekap-obj-formc.kpu.go.id/a603/pemilu/ppwp/35/10/02/20/07/3510022007015-20240217-202450--95f0cd51-f820-4ac6-bcf7-caf60a473ac2.jpg",
        "https://sirekap-obj-formc.kpu.go.id/a603/pemilu/ppwp/35/10/02/20/07/3510022007015-20240217-202449--05e712eb-1c5a-4964-aab0-a73746484861.jpg"
    ],
    "administrasi": {
        "suara_sah": 219,
        "suara_total": 225,
        "pemilih_dpt_j": 288,
        "pemilih_dpt_l": 145,
        "pemilih_dpt_p": 143,
        "pengguna_dpt_j": 221,
        "pengguna_dpt_l": 106,
        "pengguna_dpt_p": 115,
        "pengguna_dptb_j": 2,
        "pengguna_dptb_l": 1,
        "pengguna_dptb_p": 1,
        "suara_tidak_sah": 6,
        "pengguna_total_j": 225,
        "pengguna_total_l": 108,
        "pengguna_total_p": 117,
        "pengguna_non_dpt_j": 2,
        "pengguna_non_dpt_l": 1,
        "pengguna_non_dpt_p": 1
    },
    "psu": null,
    "ts": "2024-02-21 18:00:00",
    "status_suara": true,
    "status_adm": true
}