{
    "chart": null,
    "images": [
        "https://sirekap-obj-formc.kpu.go.id/539a/pemilu/ppwp/12/09/13/20/09/1209132009001-20240214-222119--32dff0d7-e0be-40ad-aebe-da8901095d49.jpg",
        null,
        "https://sirekap-obj-formc.kpu.go.id/539a/pemilu/ppwp/12/09/13/20/09/1209132009001-20240214-222128--809053fb-c332-4111-a71c-f47ce49a5356.jpg"
    ],
    "administrasi": {
        "suara_sah": 81,
        "suara_total": 81,
        "pemilih_dpt_j": 107,
        "pemilih_dpt_l": 55,
        "pemilih_dpt_p": 52,
        "pengguna_dpt_j": 81,
        "pengguna_dpt_l": 40,
        "pengguna_dpt_p": 41,
        "pengguna_dptb_j": 0,
        "pengguna_dptb_l": 0,
        "pengguna_dptb_p": 0,
        "suara_tidak_sah": 0,
        "pengguna_total_j": 81,
        "pengguna_total_l": 40,
        "pengguna_total_p": 41,
        "pengguna_non_dpt_j": 0,
        "pengguna_non_dpt_l": 0,
        "pengguna_non_dpt_p": 0
    },
    "psu": null,
    "ts": "2024-02-15 20:30:46",
    "status_suara": false,
    "status_adm": true
}