{
    "mode": "hhcw",
    "chart": {
        "null": null,
        "100025": 12,
        "100026": 174,
        "100027": 73
    },
    "images": [
        "https://sirekap-obj-formc.kpu.go.id/4e93/pemilu/ppwp/61/06/11/20/10/6106112010001-20240220-145941--da954d5c-23e4-494a-9ba0-bf10a9d62dd6.jpg",
        "https://sirekap-obj-formc.kpu.go.id/4e93/pemilu/ppwp/61/06/11/20/10/6106112010001-20240220-150205--3897191c-4ed8-40b1-ac71-afba7fffb92c.jpg",
        "https://sirekap-obj-formc.kpu.go.id/4e93/pemilu/ppwp/61/06/11/20/10/6106112010001-20240220-150410--29cfad6e-5a80-41bd-bb79-eaf842f5e419.jpg"
    ],
    "administrasi": {
        "suara_sah": 259,
        "suara_total": 268,
        "pemilih_dpt_j": 287,
        "pemilih_dpt_l": 149,
        "pemilih_dpt_p": 138,
        "pengguna_dpt_j": 265,
        "pengguna_dpt_l": 137,
        "pengguna_dpt_p": 128,
        "pengguna_dptb_j": 2,
        "pengguna_dptb_l": 1,
        "pengguna_dptb_p": 1,
        "suara_tidak_sah": 9,
        "pengguna_total_j": 268,
        "pengguna_total_l": 139,
        "pengguna_total_p": 129,
        "pengguna_non_dpt_j": 1,
        "pengguna_non_dpt_l": 1,
        "pengguna_non_dpt_p": 0
    },
    "psu": null,
    "ts": "2024-02-20 16:00:00",
    "status_suara": true,
    "status_adm": true
}