{
    "chart": {
        "null": null,
        "100025": 18,
        "100026": 114,
        "100027": 78
    },
    "images": [
        "https://sirekap-obj-formc.kpu.go.id/73c6/pemilu/ppwp/33/04/05/20/03/3304052003013-20240214-190739--15ed861a-4015-4949-8e43-a195787eb01d.jpg",
        "https://sirekap-obj-formc.kpu.go.id/73c6/pemilu/ppwp/33/04/05/20/03/3304052003013-20240214-190939--9a383e09-c06b-43f0-b15b-cdd4dc7924ca.jpg",
        "https://sirekap-obj-formc.kpu.go.id/73c6/pemilu/ppwp/33/04/05/20/03/3304052003013-20240214-191129--f97b6e98-15f2-496c-815e-f67f05ac9941.jpg"
    ],
    "administrasi": {
        "suara_sah": 210,
        "suara_total": 223,
        "pemilih_dpt_j": 273,
        "pemilih_dpt_l": 131,
        "pemilih_dpt_p": 142,
        "pengguna_dpt_j": 218,
        "pengguna_dpt_l": 101,
        "pengguna_dpt_p": 117,
        "pengguna_dptb_j": 0,
        "pengguna_dptb_l": 0,
        "pengguna_dptb_p": 0,
        "suara_tidak_sah": 13,
        "pengguna_total_j": 223,
        "pengguna_total_l": 102,
        "pengguna_total_p": 121,
        "pengguna_non_dpt_j": 5,
        "pengguna_non_dpt_l": 1,
        "pengguna_non_dpt_p": 4
    },
    "psu": null,
    "ts": "2024-02-15 00:46:45",
    "status_suara": true,
    "status_adm": true
}