{
    "mode": "hhcw",
    "chart": {
        "null": null,
        "100025": 21,
        "100026": 118,
        "100027": 54
    },
    "images": [
        "https://sirekap-obj-formc.kpu.go.id/6afa/pemilu/ppwp/33/25/09/20/21/3325092021015-20240217-203018--275ec446-aaf1-4526-9730-5177161d7f8c.jpg",
        "https://sirekap-obj-formc.kpu.go.id/6afa/pemilu/ppwp/33/25/09/20/21/3325092021015-20240218-105003--1d618000-8731-4885-b96d-7d903c1094dc.jpg",
        "https://sirekap-obj-formc.kpu.go.id/6afa/pemilu/ppwp/33/25/09/20/21/3325092021015-20240217-205054--8601e329-5d72-4906-9ff4-f820750bd513.jpg"
    ],
    "administrasi": {
        "suara_sah": 193,
        "suara_total": 200,
        "pemilih_dpt_j": 232,
        "pemilih_dpt_l": 128,
        "pemilih_dpt_p": 104,
        "pengguna_dpt_j": 197,
        "pengguna_dpt_l": 105,
        "pengguna_dpt_p": 92,
        "pengguna_dptb_j": 1,
        "pengguna_dptb_l": 1,
        "pengguna_dptb_p": 0,
        "suara_tidak_sah": 7,
        "pengguna_total_j": 200,
        "pengguna_total_l": 108,
        "pengguna_total_p": 92,
        "pengguna_non_dpt_j": 2,
        "pengguna_non_dpt_l": 2,
        "pengguna_non_dpt_p": 0
    },
    "psu": null,
    "ts": "2024-02-21 12:00:00",
    "status_suara": true,
    "status_adm": true
}